netrun/config/__init__.py
netrun/config/base.py
netrun/config/cache.py
netrun/config/exceptions.py
netrun/config/keyvault.py
netrun/config/multi_vault.py
netrun/config/py.typed
netrun/config/settings_source.py
netrun/config/types.py
netrun/config/validators.py
netrun_config/__init__.py
netrun_config-2.0.0.dist-info/METADATA
netrun_config-2.0.0.dist-info/WHEEL
netrun_config-2.0.0.dist-info/licenses/LICENSE
netrun_config-2.0.0.dist-info/RECORD
