Metadata-Version: 2.4
Name: netrun-config
Version: 2.0.0
Summary: Unified configuration management for Netrun Systems portfolio with TTL caching and multi-vault support
Project-URL: Homepage, https://github.com/netrunsystems/netrun-config
Project-URL: Documentation, https://docs.netrunsystems.com/config
Project-URL: Repository, https://github.com/netrunsystems/netrun-config
Project-URL: Issues, https://github.com/netrunsystems/netrun-config/issues
Author-email: Daniel Garza <daniel@netrunsystems.com>
License: MIT
License-File: LICENSE
Keywords: azure,caching,configuration,keyvault,multi-vault,namespace,pydantic,settings
Classifier: Development Status :: 5 - Production/Stable
Classifier: Framework :: Pydantic
Classifier: Framework :: Pydantic :: 2
Classifier: Intended Audience :: Developers
Classifier: License :: OSI Approved :: MIT License
Classifier: Programming Language :: Python :: 3
Classifier: Programming Language :: Python :: 3.10
Classifier: Programming Language :: Python :: 3.11
Classifier: Programming Language :: Python :: 3.12
Classifier: Topic :: Software Development :: Libraries :: Python Modules
Requires-Python: >=3.10
Requires-Dist: pydantic-settings>=2.0.0
Requires-Dist: pydantic>=2.0.0
Provides-Extra: all
Requires-Dist: azure-identity>=1.15.0; extra == 'all'
Requires-Dist: azure-keyvault-secrets>=4.8.0; extra == 'all'
Requires-Dist: netrun-errors>=2.0.0; extra == 'all'
Requires-Dist: netrun-logging>=2.0.0; extra == 'all'
Provides-Extra: azure
Requires-Dist: azure-identity>=1.15.0; extra == 'azure'
Requires-Dist: azure-keyvault-secrets>=4.8.0; extra == 'azure'
Provides-Extra: dev
Requires-Dist: black>=23.0.0; extra == 'dev'
Requires-Dist: mypy>=1.5.0; extra == 'dev'
Requires-Dist: pytest-asyncio>=0.21.0; extra == 'dev'
Requires-Dist: pytest-cov>=4.1.0; extra == 'dev'
Requires-Dist: pytest>=7.4.0; extra == 'dev'
Requires-Dist: ruff>=0.1.0; extra == 'dev'
Provides-Extra: errors
Requires-Dist: netrun-errors>=2.0.0; extra == 'errors'
Provides-Extra: logging
Requires-Dist: netrun-logging>=2.0.0; extra == 'logging'
